kisho/__init__.py
kisho/traced.py
kisho-0.3.13.dist-info/METADATA
kisho-0.3.13.dist-info/WHEEL
kisho-0.3.13.dist-info/top_level.txt
kisho-0.3.13.dist-info/RECORD
