Metadata-Version: 2.1
Name: kisho
Version: 0.3.13
Summary: A tracing library for OpenAI API calls and custom functions
Home-page: https://github.com/kisholabs/sdk-v3
Author: Aryan Jain
Author-email: aryan@kisho.app
Classifier: Development Status :: 3 - Alpha
Classifier: Intended Audience :: Developers
Classifier: License :: OSI Approved :: MIT License
Classifier: Programming Language :: Python :: 3
Requires-Python: >=3.7
Requires-Dist: openai>=0.27.0
Requires-Dist: requests>=2.25.0
Requires-Dist: fastapi>=0.68.0
Requires-Dist: uvicorn>=0.15.0
Requires-Dist: networkx>=2.5
Requires-Dist: matplotlib>=3.3.0
Requires-Dist: python-dotenv>=0.19.0
